aiokilogram/__init__.py
aiokilogram/action.py
aiokilogram/bot.py
aiokilogram/data.py
aiokilogram/dispatcher.py
aiokilogram/errors.py
aiokilogram/handler.py
aiokilogram/messenger.py
aiokilogram/page.py
aiokilogram/py.typed
aiokilogram/registration.py
aiokilogram/settings.py
aiokilogram-0.1.3.dist-info/LICENSE
aiokilogram-0.1.3.dist-info/METADATA
aiokilogram-0.1.3.dist-info/WHEEL
aiokilogram-0.1.3.dist-info/top_level.txt
aiokilogram-0.1.3.dist-info/RECORD
