Metadata-Version: 2.1
Name: aiokilogram
Version: 0.1.3
Summary: Convenience tools and wrappers for aiogram
Home-page: https://github.com/altvod/aiokilogram
Author: Grigory Statsenko
Author-email: grisha100@gmail.com
Project-URL: Bug Tracker, https://github.com/altvod/aiokilogram/issues
Keywords: telegram,aiogram
Classifier: Development Status :: 4 - Beta
Classifier: Intended Audience :: Developers
Classifier: Topic :: Software Development :: Libraries :: Python Modules
Classifier: Programming Language :: Python :: 3
Classifier: Programming Language :: Python :: 3 :: Only
Classifier: Programming Language :: Python :: 3.9
Classifier: Programming Language :: Python :: 3.10
Classifier: Programming Language :: Python :: 3.11
Classifier: License :: OSI Approved :: MIT License
Classifier: Operating System :: OS Independent
Requires-Python: >=3.9
License-File: LICENSE
Requires-Dist: aiogram
Requires-Dist: attrs
Requires-Dist: emoji
Provides-Extra: build
Requires-Dist: build ; extra == 'build'
Requires-Dist: twine ; extra == 'build'
Provides-Extra: testing
Requires-Dist: mypy ; extra == 'testing'
Requires-Dist: pytest ; extra == 'testing'
